{
  "father": "calibration",
  "name": "drying_consumables",
  "type": "Grid",
  "head_grid": {
    "name": "Head Grid",
    "type": "Grid",
    "width": 970,
    "height": 50,
    "column": 0,
    "row": 0,
    "columnspan": 1,
    "rowspan": 1,
    "v_width": 970,
    "v_height": 50,
    "v_column": 0,
    "v_row": 0,
    "v_columnspan": 1,
    "v_rowspan": 1,
    "children": {
      "go_bcak": {
        "name": "Go Back",
        "type": "Button",
        "icon": "back",
        "hexpand": "False",
        "vexpand": "False",
        "button_width": 150,
        "button_height": 50,
        "v_button_width": 150,
        "v_button_height": 50,
        "width": 50,
        "height": 50,
        "column": 0,
        "row": 0,
        "columnspan": 1,
        "rowspan": 1,
        "v_width": 50,
        "v_height": 50,
        "v_column": 0,
        "v_row": 0,
        "v_columnspan": 1,
        "v_rowspan": 1
      },
      "drying_consumables_label": {
        "name": "Drying Consumables Label",
        "type": "Label",
        "value": "烘干耗材",
        "column": 1,
        "row": 0,
        "columnspan": 1,
        "rowspan": 1,
        "v_column": 1,
        "v_row": 0,
        "v_columnspan": 1,
        "v_rowspan": 1
      }
    }
  },
  "drying_consumables_body_grid": {
    "name": "Drying Consumables Body grid",
    "type": "Grid",
    "width": 940,
    "height": 500,
    "column": 0,
    "row": 1,
    "columnspan": 4,
    "rowspan": 5,
    "v_width": 940,
    "v_height": 500,
    "v_column": 0,
    "v_row": 1,
    "v_columnspan": 4,
    "v_rowspan": 5,
    "children": {
      "drying_consumables_message_grid": {
        "name": "Drying Consumables Message Grid",
        "type": "Grid",
        "width": 550,
        "height": 500,
        "column": 0,
        "row": 0,
        "columnspan": 3,
        "rowspan": 7,
        "v_width": 550,
        "v_height": 500,
        "v_column": 0,
        "v_row": 0,
        "v_columnspan": 3,
        "v_rowspan": 7,
        "children": {
          "consumables_type_label": {
            "name": "Consumables Label",
            "type": "Label",
            "value": "耗材类型",
            "column": 0,
            "row": 0,
            "columnspan": 1,
            "rowspan": 1,
            "v_column": 0,
            "v_row": 0,
            "v_columnspan": 1,
            "v_rowspan": 1
          },
          "consumables_select": {
            "name": "Consumables Select",
            "type": "ComboBoxText",
            "width": 300,
            "height": 25,
            "column": 0,
            "row": 1,
            "columnspan": 1,
            "rowspan": 1,
            "v_width": 300,
            "v_height": 25,
            "v_column": 0,
            "v_row": 1,
            "v_columnspan": 1,
            "v_rowspan": 1,
            "style": "consumables_select"
          },
          "drying_consumables_temperature": {
            "name": "Drying Consumables Temperature",
            "type": "Button",
            "value": "66℃",
            "icon": "hotbed_temperature",
            "hexpand": "False",
            "vexpand": "False",
            "position": "LEFT",
            "button_width": 60,
            "button_height": 25,
            "v_button_width": 60,
            "v_button_height": 25,
            "width": 25,
            "height": 25,
            "column": 1,
            "row": 1,
            "columnspan": 1,
            "rowspan": 1,
            "v_width": 25,
            "v_height": 25,
            "v_column": 1,
            "v_row": 1,
            "v_columnspan": 1,
            "v_rowspan": 1
          },
          "dtying_consumables_time": {
            "name": "Drying Consumables Time",
            "type": "Button",
            "value": "12H",
            "icon": "clock",
            "hexpand": "False",
            "vexpand": "False",
            "position": "LEFT",
            "button_width": 60,
            "button_height": 25,
            "v_button_width": 60,
            "v_button_height": 25,
            "width": 25,
            "height": 25,
            "column": 2,
            "row": 1,
            "columnspan": 1,
            "rowspan": 1,
            "v_width": 25,
            "v_height": 25,
            "v_column": 2,
            "v_row": 1,
            "v_columnspan": 1,
            "v_rowspan": 1
          },
          "tag_white": {
            "name": "Tag White",
            "type": "Image",
            "src": "images/tag_white.png",
            "width": 520,
            "height": 3,
            "column": 0,
            "row": 2,
            "columnspan": 3,
            "rowspan": 1,
            "v_width": 520,
            "v_height": 3,
            "v_column": 0,
            "v_row": 2,
            "v_columnspan": 3,
            "v_rowspan": 1
          },
          "drying_consumables_maintenance_message": {
            "name": "Drying Consumables Message",
            "type": "TextView",
            "value": "步骤1：\\n步骤2：\\n步骤3：\\n步骤4：\\n步骤5：\\n",
            "column": 0,
            "row": 3,
            "columnspan": 3,
            "rowspan": 1,
            "v_column": 0,
            "v_row": 3,
            "v_columnspan": 3,
            "v_rowspan": 1
          }
        }
      },
      "drying_consumables_image_grid": {
        "name": "Drying Consumables Image Grid",
        "type": "Grid",
        "column_homogeneous": "True",
        "row_homogeneous": "True",
        "width": 400,
        "height": 420,
        "column": 3,
        "row": 0,
        "columnspan": 2,
        "rowspan": 6,
        "v_width": 400,
        "v_height": 420,
        "v_column": 3,
        "v_row": 0,
        "v_columnspan": 2,
        "v_rowspan": 6,
        "children": {
          "drying_consumables_image": {
            "name": "Drying Consumables Image",
            "type": "Image",
            "src": "images/drying_consumables.jpg",
            "width": 360,
            "height": 400,
            "column": 0,
            "row": 0,
            "columnspan": 1,
            "rowspan": 1,
            "v_width": 360,
            "v_height": 400,
            "v_column": 0,
            "v_row": 0,
            "v_columnspan": 1,
            "v_rowspan": 1
          }
        }
      },
      "drying_consumables_start_button": {
        "name": "Drying Consumables Start Button",
        "type": "Button",
        "value": "准备",
        "hexpand": "False",
        "vexpand": "False",
        "button_width": 400,
        "button_height": 60,
        "v_button_width": 400,
        "v_button_height": 60,
        "column": 3,
        "row": 6,
        "columnspan": 2,
        "rowspan": 1,
        "v_column": 3,
        "v_row": 6,
        "v_columnspan": 2,
        "v_rowspan": 1,
        "style": "next_level"
      }
    }
  }
}