{
  "father": "menu",
  "name": "print_menu",
  "type": "Grid",
  "children": {
    "v_progress_bar": {
      "name": "V Progress Bar",
      "type": "ProgressBar",
      "width": 30,
      "height": 30,
      "column": 0,
      "row": 1,
      "columnspan": 5,
      "rowspan": 1,
      "v_width": 560,
      "v_height": 10,
      "v_column": 0,
      "v_row": 0,
      "v_columnspan": 4,
      "v_rowspan": 1
    },
    "left_up_grid": {
      "name": "Left Up Grid",
      "type": "Grid",
      "column_homogeneous": "True",
      "width": 330,
      "height": 330,
      "column": 0,
      "row": 0,
      "columnspan": 3,
      "rowspan": 3,
      "v_width": 400,
      "v_height": 200,
      "v_column": 0,
      "v_row": 1,
      "v_columnspan": 2,
      "v_rowspan": 5,
      "children": {
        "print_file_list_button": {
          "name": "Print File List Button",
          "type": "Button",
          "hexpand": "False",
          "vexpand": "False",
          "button_width": 300,
          "button_height": 300,
          "v_button_width": 180,
          "v_button_height": 200,
          "column": 0,
          "row": 0,
          "columnspan": 1,
          "rowspan": 1,
          "v_column": 0,
          "v_row": 0,
          "v_columnspan": 1,
          "v_rowspan": 1,
          "panel": "print_file_list",
          "style": "print_file_list_button",
          "children": {
            "print_file_list_button_grid": {
              "name": "Print File List Button Grid",
              "type": "Grid",
              "width": 300,
              "height": 300,
              "v_width": 180,
              "v_height": 200,
              "camera_rec_icon": {
                "name": "Camear Rec Icon",
                "type": "Image",
                "src": "images/camera_rec.png",
                "width": 30,
                "height": 30,
                "column": 0,
                "row": 0,
                "columnspan": 1,
                "rowspan": 1,
                "v_width": 30,
                "v_height": 30,
                "v_column": 0,
                "v_row": 0,
                "v_columnspan": 1,
                "v_rowspan": 1
              },
              "space_label": {
                "name": "Space Label",
                "type": "Label",
                "value": "占位符",
                "column": 1,
                "row": 0,
                "columnspan": 1,
                "rowspan": 1,
                "v_column": 1,
                "v_row": 0,
                "v_columnspan": 1,
                "v_rowspan": 1
              },
              "file_label": {
                "name": "File Label",
                "type": "Label",
                "value": "File",
                "column": 2,
                "row": 0,
                "columnspan": 1,
                "rowspan": 1,
                "v_column": 2,
                "v_row": 0,
                "v_columnspan": 1,
                "v_rowspan": 1
              },
              "settings_right_arrow_icon": {
                "name": "Right Arrow Icon",
                "type": "Image",
                "src": "images/right_arrow.png",
                "width": 20,
                "height": 30,
                "column": 3,
                "row": 0,
                "columnspan": 1,
                "rowspan": 1,
                "v_width": 20,
                "v_height": 30,
                "v_column": 3,
                "v_row": 0,
                "v_columnspan": 1,
                "v_rowspan": 1
              },
              "print_modeling_graphics": {
                "name": "Print Modeling Graphics",
                "type": "Image",
                "src": "images/no_model_image.png",
                "width": 300,
                "height": 300,
                "column": 0,
                "row": 1,
                "columnspan": 4,
                "rowspan": 4,
                "v_width": 200,
                "v_height": 200,
                "v_column": 0,
                "v_row": 1,
                "v_columnspan": 4,
                "v_rowspan": 4
              },
              "print_file_name": {
                "name": "Print File Name",
                "type": "Label",
                "value": "3D打印模型文件名",
                "column": 0,
                "row": 5,
                "columnspan": 4,
                "rowspan": 1,
                "v_column": 0,
                "v_row": 5,
                "v_columnspan": 4,
                "v_rowspan": 1
              }
            }
          }
        }
      }
    },
    "temperature_grid": {
      "name": "Temperature Grid",
      "type": "Grid",
      "width": 440,
      "height": 360,
      "column": 3,
      "row": 0,
      "columnspan": 4,
      "rowspan": 3,
      "v_width": 400,
      "v_height": 180,
      "v_column": 0,
      "v_row": 6,
      "v_columnspan": 2,
      "v_rowspan": 5,
      "children": {
        "printer_temperature_grid": {
          "name": "Printer Temperature Grid",
          "type": "Grid",
          "width": 310,
          "height": 360,
          "column": 0,
          "row": 0,
          "columnspan": 3,
          "rowspan": 3,
          "v_width": 180,
          "v_height": 180,
          "v_column": 0,
          "v_row": 0,
          "v_columnspan": 3,
          "v_rowspan": 3,
          "children": {
            "chassis_temperature": {
              "name": "Chassis Temperature",
              "type": "Button",
              "value": "60℃",
              "icon": "chassis_temperature",
              "hexpand": "False",
              "vexpand": "False",
              "position": "LEFT",
              "width": 30,
              "height": 30,
              "column": 0,
              "row": 0,
              "columnspan": 1,
              "rowspan": 1,
              "v_width": 30,
              "v_height": 30,
              "v_column": 0,
              "v_row": 0,
              "v_columnspan": 1,
              "v_rowspan": 1,
              "panel": "chassis_temperature"
            },
            "heater_bedtemperature": {
              "name": "Heater Bed Temperature",
              "type": "Button",
              "value": "60℃",
              "icon": "hotbed_temperature",
              "hexpand": "False",
              "vexpand": "False",
              "position": "LEFT",
              "width": 30,
              "height": 30,
              "column": 0,
              "row": 1,
              "columnspan": 1,
              "rowspan": 1,
              "v_width": 30,
              "v_height": 30,
              "v_column": 0,
              "v_row": 1,
              "v_columnspan": 1,
              "v_rowspan": 1,
              "panel": "heater_bed_temperature"
            }
          }
        },
        "tag_white": {
          "name": "Tag White",
          "type": "Image",
          "src": "images/tag_white.png",
          "width": 3,
          "height": 300,
          "column": 3,
          "row": 0,
          "columnspan": 1,
          "rowspan": 3,
          "v_width": 3,
          "v_height": 360,
          "v_column": 3,
          "v_row": 0,
          "v_columnspan": 1,
          "v_rowspan": 3
        },
        "nozzle_extruder": {
          "name": "Nozzle Extruder",
          "type": "Button",
          "hexpand": "False",
          "vexpand": "False",
          "column": 4,
          "row": 0,
          "columnspan": 1,
          "rowspan": 3,
          "v_width": 140,
          "v_height": 160,
          "v_column": 4,
          "v_row": 0,
          "v_columnspan": 1,
          "v_rowspan": 3,
          "children": {
            "nozzle_extruder_temperature_grid": {
              "name": "Nozzle Extruder Temperature Grid",
              "type": "Grid",
              "width": 140,
              "height": 360,
              "column": 4,
              "row": 0,
              "columnspan": 1,
              "rowspan": 3,
              "v_width": 140,
              "v_height": 160,
              "v_column": 0,
              "v_row": 0,
              "v_columnspan": 1,
              "v_rowspan": 1,
              "children": {
                "nozzle_extruder_image": {
                  "name": "Nozzle Extrude Image",
                  "type": "Image",
                  "src": "images/nozzle_extruder.png",
                  "width": 60,
                  "height": 90,
                  "column": 0,
                  "row": 0,
                  "columnspan": 1,
                  "rowspan": 3,
                  "v_width": 60,
                  "v_height": 90,
                  "v_column": 0,
                  "v_row": 0,
                  "v_columnspan": 1,
                  "v_rowspan": 3
                },
                "extruder_temperature": {
                  "name": "Extruder Temperature",
                  "type": "Button",
                  "value": "L 60℃",
                  "icon": "nozzle_temperature",
                  "hexpand": "False",
                  "vexpand": "False",
                  "position": "LEFT",
                  "width": 30,
                  "height": 30,
                  "column": 0,
                  "row": 3,
                  "columnspan": 1,
                  "rowspan": 1,
                  "v_width": 30,
                  "v_height": 30,
                  "v_column": 0,
                  "v_row": 3,
                  "v_columnspan": 1,
                  "v_rowspan": 1
                },
                "extruder1_temperature": {
                  "name": " Extruder1 Temperature",
                  "type": "Button",
                  "value": "R 60℃",
                  "icon": "nozzle_temperature",
                  "hexpand": "False",
                  "vexpand": "False",
                  "position": "LEFT",
                  "width": 30,
                  "height": 30,
                  "column": 0,
                  "row": 4,
                  "columnspan": 1,
                  "rowspan": 1,
                  "v_width": 30,
                  "v_height": 30,
                  "v_column": 0,
                  "v_row": 4,
                  "v_columnspan": 1,
                  "v_rowspan": 1
                }
              }
            }
          },
          "panel": "extruder_temperature"
        }
      }
    },
    "messages_control_grid": {
      "name": "Messages Control Grid",
      "type": "Grid",
      "width": 660,
      "height": 120,
      "column": 0,
      "row": 3,
      "columnspan": 6,
      "rowspan": 1,
      "v_width": 160,
      "v_height": 400,
      "v_column": 2,
      "v_row": 1,
      "v_columnspan": 1,
      "v_rowspan": 7,
      "children": {
        "print_inner_grid": {
          "name": "Print Inner Grid",
          "type": "Grid",
          "width": 330,
          "height": 120,
          "column": 0,
          "row": 0,
          "columnspan": 3,
          "rowspan": 1,
          "v_width": 100,
          "v_height": 100,
          "v_column": 0,
          "v_row": 0,
          "v_columnspan": 1,
          "v_rowspan": 3,
          "children": {
            "percentage_progress": {
              "name": "Percentage Progress",
              "type": "Label",
              "value": "70",
              "column": 0,
              "row": 0,
              "columnspan": 1,
              "rowspan": 1,
              "v_column": 0,
              "v_row": 0,
              "v_columnspan": 2,
              "v_rowspan": 1
            },
            "space_label": {
              "name": "Space Label",
              "type": "Label",
              "value": "占位符",
              "column": 1,
              "row": 0,
              "columnspan": 1,
              "rowspan": 1,
              "v_column": 0,
              "v_row": 2,
              "v_columnspan": 2,
              "v_rowspan": 1
            },
            "print_speed": {
              "name": "Print Speed",
              "type": "Label",
              "value": "100%%",
              "column": 3,
              "row": 0,
              "columnspan": 1,
              "rowspan": 1,
              "v_column": 0,
              "v_row": 2,
              "v_columnspan": 2,
              "v_rowspan": 1
            },
            "print_layers": {
              "name": "Print Layers",
              "type": "Label",
              "value": "Layers : 0 | 50",
              "column": 3,
              "row": 0,
              "columnspan": 1,
              "rowspan": 1,
              "v_column": 0,
              "v_row": 3,
              "v_columnspan": 2,
              "v_rowspan": 1
            },
            "remaining_time": {
              "name": "Remaining Time",
              "type": "Label",
              "value": "Time",
              "column": 4,
              "row": 0,
              "columnspan": 1,
              "rowspan": 1,
              "v_column": 0,
              "v_row": 4,
              "v_columnspan": 2,
              "v_rowspan": 1
            },
            "h_progress_bar": {
              "name": "H Progress Bar",
              "type": "ProgressBar",
              "width": 30,
              "height": 30,
              "column": 0,
              "row": 1,
              "columnspan": 5,
              "rowspan": 1,
              "v_width": 50,
              "v_height": 30,
              "v_column": 0,
              "v_row": 7,
              "v_columnspan": 1,
              "v_rowspan": 1
            },
            "print_state": {
              "name": "Print State",
              "type": "Label",
              "value": "Printing",
              "column": 0,
              "row": 2,
              "columnspan": 3,
              "rowspan": 1,
              "v_column": 0,
              "v_row": 5,
              "v_columnspan": 2,
              "v_rowspan": 1
            }
          }
        },
        "skip_button": {
          "name": "Skip Button",
          "type": "Button",
          "value": "Skip",
          "icon": "skip",
          "hexpand": "False",
          "vexpand": "True",
          "button_width": 100,
          "button_height": 100,
          "v_button_width": 100,
          "v_button_height": 110,
          "width": 50,
          "height": 50,
          "column": 4,
          "row": 0,
          "columnspan": 1,
          "rowspan": 1,
          "v_width": 50,
          "v_height": 50,
          "v_column": 0,
          "v_row": 3,
          "v_columnspan": 1,
          "v_rowspan": 1,
          "style": "print_menu_button"
        },
        "pause_button": {
          "name": "Pause Button",
          "type": "Button",
          "value": "Pause",
          "method": "pause_confirm",
          "icon": "pause",
          "hexpand": "False",
          "vexpand": "True",
          "button_width": 100,
          "button_height": 100,
          "v_button_width": 100,
          "v_button_height": 110,
          "width": 50,
          "height": 50,
          "column": 5,
          "row": 0,
          "columnspan": 1,
          "rowspan": 1,
          "v_width": 50,
          "v_height": 50,
          "v_column": 0,
          "v_row": 4,
          "v_columnspan": 1,
          "v_rowspan": 1,
          "style": "print_menu_button"
        },
        "cancel_button": {
          "name": "Cancel Button",
          "type": "Button",
          "value": "Stop",
          "method": "cancel_confirm",
          "icon": "stop",
          "hexpand": "False",
          "vexpand": "True",
          "button_width": 100,
          "button_height": 100,
          "v_button_width": 100,
          "v_button_height": 110,
          "width": 50,
          "height": 50,
          "column": 6,
          "row": 0,
          "columnspan": 1,
          "rowspan": 1,
          "v_width": 50,
          "v_height": 50,
          "v_column": 0,
          "v_row": 5,
          "v_columnspan": 1,
          "v_rowspan": 1,
          "style": "print_menu_button"
        }
      }
    },
    "right_down_grid": {
      "name": "Right Down Grid",
      "type": "Grid",
      "width": 110,
      "height": 110,
      "column": 6,
      "row": 3,
      "columnspan": 1,
      "rowspan": 1,
      "v_width": 160,
      "v_height": 230,
      "v_column": 2,
      "v_row": 8,
      "v_columnspan": 1,
      "v_rowspan": 2,
      "children": {
        "messages_assistant": {
          "name": "Messages Assistant",
          "type": "Button",
          "icon": "messages_assistant",
          "button_width": 100,
          "button_height": 100,
          "v_button_width": 100,
          "v_button_height": 230,
          "width": 100,
          "height": 100,
          "column": 0,
          "row": 0,
          "columnspan": 1,
          "rowspan": 1,
          "v_width": 100,
          "v_height": 100,
          "v_column": 0,
          "v_row": 0,
          "v_columnspan": 1,
          "v_rowspan": 1,
          "panel": "messages_menu"
        }
      }
    }
  }
}